selenew/__init__.py
selenew/base/__init__.py
selenew/base/page.py
selenew/base/webdriver.py
selenew/common/__init__.py
selenew/common/constants.py
selenew/common/exceptions.py
selenew/common/logger.py
selenew-0.0.1.dist-info/LICENSE
selenew-0.0.1.dist-info/METADATA
selenew-0.0.1.dist-info/WHEEL
selenew-0.0.1.dist-info/top_level.txt
selenew-0.0.1.dist-info/RECORD
