Metadata-Version: 2.1
Name: selenew
Version: 0.0.1
Summary: SeleNew is a framework over Selenium to simplify UI Test Automation
Author: Toghrul Mirzayev
Author-email: togrul.mirzoev@gmail.com
Keywords: testing,selenium,selenew,browser,ui,qa
Classifier: Development Status :: 2 - Pre-Alpha
Classifier: Intended Audience :: Developers
Classifier: License :: OSI Approved :: MIT License
Classifier: Programming Language :: Python :: 3
Classifier: Programming Language :: Python :: 3.7
Classifier: Programming Language :: Python :: 3.8
Classifier: Programming Language :: Python :: 3.9
Classifier: Topic :: Software Development :: Testing
Requires-Python: >=3.7
License-File: LICENSE
Requires-Dist: selenium (>=4.4.3)
Requires-Dist: webdriver-manager (>=3.8.5)
Requires-Dist: colorama (>=0.4.4)
